simple_service/__init__.py
simple_service/simple_service.py
ops_py_example_code_template-0.0.3.dist-info/METADATA
ops_py_example_code_template-0.0.3.dist-info/WHEEL
ops_py_example_code_template-0.0.3.dist-info/top_level.txt
ops_py_example_code_template-0.0.3.dist-info/RECORD
