Metadata-Version: 2.1
Name: ops-py-example-code-template
Version: 0.0.3
Summary: Template and testing purposes
License: The MIT License (MIT)
Requires-Dist: requests
